{
  "acc_hotel_001": {
    "name": "Danube Grand Hotel",
    "type": "hotel",
    "price": 120,
    "available_rooms": 25,
    "rooms": 80,
    "persons": 2,
    "travelers_rating": 4.6,
    "rating": 4,
    "description": "Elegant hotel near the river with wellness services.",
    "continent": "Europe",
    "country": "Hungary",
    "zip_code": "1051",
    "city": "Budapest",
    "address": "River Street 12",
    "comments": ["Great location", "Friendly staff"],
    "services": ["breakfast", "wellness", "balcony", "pet-friendly"],
    "email": "info@danubegrandhotel.com",
    "phone_number": "+3612345678"
  },
  "acc_hotel_002": {
    "name": "Alpine View Hotel",
    "type": "hotel",
    "price": 150,
    "available_rooms": 10,
    "rooms": 60,
    "persons": 2,
    "travelers_rating": 4.8,
    "rating": 5,
    "description": "Luxury hotel with mountain panorama.",
    "continent": "Europe",
    "country": "Austria",
    "zip_code": "6020",
    "city": "Innsbruck",
    "address": "Mountain Road 8",
    "comments": ["Amazing view", "Top wellness"],
    "services": ["breakfast", "wellness", "balcony"],
    "email": "contact@alpineview.at",
    "phone_number": "+43512345678"
  },
  "acc_hotel_003": {
    "name": "City Lights Hotel",
    "type": "hotel",
    "price": 95,
    "available_rooms": 40,
    "rooms": 100,
    "persons": 2,
    "travelers_rating": 4.2,
    "rating": 3,
    "description": "Modern hotel in the city center.",
    "continent": "Europe",
    "country": "Germany",
    "zip_code": "10115",
    "city": "Berlin",
    "address": "Central Avenue 5",
    "comments": ["Clean rooms", "Good value"],
    "services": ["breakfast", "pet-friendly"],
    "email": "info@citylightshotel.de",
    "phone_number": "+4930123456"
  },
  "acc_hotel_004": {
    "name": "Ocean Breeze Resort",
    "type": "hotel",
    "price": 180,
    "available_rooms": 15,
    "rooms": 70,
    "persons": 2,
    "travelers_rating": 4.9,
    "rating": 5,
    "description": "Beachfront hotel with premium services.",
    "continent": "Europe",
    "country": "Spain",
    "zip_code": "08002",
    "city": "Barcelona",
    "address": "Seaside Blvd 22",
    "comments": ["Perfect beach", "Excellent food"],
    "services": ["breakfast", "wellness", "balcony"],
    "email": "hello@oceanbreezeresort.es",
    "phone_number": "+34931234567"
  },
  "acc_guesthouse_001": {
    "name": "Green Garden Guesthouse",
    "type": "guesthouse",
    "price": 60,
    "rooms": 5,
    "persons": 2,
    "capacity": 10,
    "travelers_rating": 4.4,
    "description": "Cozy guesthouse with a peaceful garden.",
    "continent": "Europe",
    "country": "Hungary",
    "zip_code": "8230",
    "city": "Balatonfüred",
    "address": "Garden Lane 3",
    "comments": ["Quiet place", "Very clean"],
    "services": ["breakfast", "pet-friendly"],
    "email": "contact@greengarden.hu",
    "phone_number": "+36201234567"
  },
  "acc_guesthouse_002": {
    "name": "Old Town Guesthouse",
    "type": "guesthouse",
    "price": 55,
    "rooms": 4,
    "persons": 2,
    "capacity": 8,
    "travelers_rating": 4.1,
    "description": "Charming guesthouse in the old town.",
    "continent": "Europe",
    "country": "Czech Republic",
    "zip_code": "11000",
    "city": "Prague",
    "address": "Historic Street 9",
    "comments": ["Nice host", "Central location"],
    "services": ["breakfast"],
    "email": "info@oldtownguest.cz",
    "phone_number": "+42021234567"
  },
  "acc_guesthouse_003": {
    "name": "Mountain Nest Guesthouse",
    "type": "guesthouse",
    "price": 70,
    "rooms": 6,
    "persons": 2,
    "capacity": 12,
    "travelers_rating": 4.7,
    "description": "Guesthouse surrounded by nature.",
    "continent": "Europe",
    "country": "Slovakia",
    "zip_code": "03101",
    "city": "Liptovsky Mikulas",
    "address": "Forest Road 15",
    "comments": ["Great hiking", "Peaceful"],
    "services": ["pet-friendly", "balcony"],
    "email": "stay@mountainnests.sk",
    "phone_number": "+42144123456"
  },
  "acc_guesthouse_004": {
    "name": "Sunny Stay Guesthouse",
    "type": "guesthouse",
    "price": 65,
    "rooms": 5,
    "persons": 2,
    "capacity": 10,
    "travelers_rating": 4.3,
    "description": "Bright guesthouse close to downtown.",
    "continent": "Europe",
    "country": "Italy",
    "zip_code": "00184",
    "city": "Rome",
    "address": "Via Sole 18",
    "comments": ["Nice rooms", "Helpful staff"],
    "services": ["breakfast", "balcony"],
    "email": "info@sunnystay.it",
    "phone_number": "+39061234567"
  },
  "acc_guesthouse_005": {
    "name": "Riverbank Guesthouse",
    "type": "guesthouse",
    "price": 75,
    "rooms": 6,
    "persons": 2,
    "capacity": 14,
    "travelers_rating": 4.5,
    "description": "Guesthouse with river view.",
    "continent": "Europe",
    "country": "France",
    "zip_code": "67000",
    "city": "Strasbourg",
    "address": "Quai River 7",
    "comments": ["Beautiful view", "Great breakfast"],
    "services": ["breakfast", "pet-friendly"],
    "email": "contact@riverbank.fr",
    "phone_number": "+33388123456"
  }
}
